data_anchor_py/__init__.py
data_anchor_py/core.py
data_anchor_py/decorators.py
data_anchor_py/exceptions.py
data_anchor_py/tests/__init__.py
data_anchor_py/tests/test_core.py
data_anchor_py/tests/test_integration.py
data_anchor_py/utils.py
data_anchor_py-0.0.23.dist-info/LICENSE
data_anchor_py-0.0.23.dist-info/METADATA
data_anchor_py-0.0.23.dist-info/WHEEL
data_anchor_py-0.0.23.dist-info/RECORD
