Metadata-Version: 2.3
Name: data-anchor-py
Version: 0.0.23
Summary: A way to create shared dataclasses in python for multiprocessing and multi threading real time applications
License: MIT
Keywords: dataclasses,shared dataclasses,multiprocessing,multithreading,real time applications,dataanchor
Author: GitMohit007 mohitkrishna010@gmail.com
Requires-Python: >=3.8
Classifier: License :: OSI Approved :: MIT License
Classifier: Programming Language :: Python :: 3
Classifier: Programming Language :: Python :: 3.8
Classifier: Programming Language :: Python :: 3.9
Classifier: Programming Language :: Python :: 3.10
Classifier: Programming Language :: Python :: 3.11
Classifier: Programming Language :: Python :: 3.12
Classifier: Programming Language :: Python :: 3.13
